{"expireTime":9007200844110481000,"key":"create-remote-file-node-https://www.julienlucas.ovh/wp-content/uploads/2011/08/gratitude.jpg","val":{"date":"Wed, 13 May 2020 11:31:30 GMT","content-type":"image/jpeg","content-length":"251279","connection":"close","server":"Apache","last-modified":"Thu, 23 Apr 2020 17:59:42 GMT","accept-ranges":"bytes","cache-control":"max-age=900","expires":"Wed, 13 May 2020 11:46:30 GMT","x-iplb-instance":"32681","set-cookie":["SERVERID112363=2820160|Xrval|Xrval; path=/"]}}